stardust/__init__.py
stardust/config.ini
stardust/config.py
stardust/command/__init__.py
stardust/command/export.py
stardust/components/__init__.py
stardust/components/frame.py
stardust/components/annotations/__init__.py
stardust/components/annotations/audio.py
stardust/components/annotations/base_annotation.py
stardust/components/annotations/box.py
stardust/components/annotations/box3d.py
stardust/components/annotations/input.py
stardust/components/annotations/line.py
stardust/components/annotations/point.py
stardust/components/annotations/point3d.py
stardust/components/annotations/polygon.py
stardust/components/annotations/semantic_segmentation_3d.py
stardust/components/annotations/text.py
stardust/components/annotations/video.py
stardust/components/attachment/__init__.py
stardust/components/attachment/attachment.py
stardust/components/attachment/image.py
stardust/components/attachment/pointcloud.py
stardust/components/camera/__init__.py
stardust/components/camera/camera.py
stardust/components/ego/__init__.py
stardust/components/ego/ego.py
stardust/convertion/__init__.py
stardust/convertion/to_coco/__init__.py
stardust/convertion/to_coco/coco_demo.py
stardust/convertion/to_coco/to_coco.py
stardust/convertion/to_kitti/__init__.py
stardust/convertion/to_kitti/to_kitti.py
stardust/convertion/to_pandaset/__init__.py
stardust/convertion/to_pandaset/to_pandaset.py
stardust/file/__init__.py
stardust/file/download_files.py
stardust/file/file.py
stardust/geometry/__init__.py
stardust/geometry/ops2d/__init__.py
stardust/geometry/ops3d/__init__.py
stardust/geometry/ops3d/bbox/__init__.py
stardust/geometry/ops3d/bbox/box_size_alignment.py
stardust/geometry/ops3d/bbox/occlusion.py
stardust/geometry/ops3d/bbox/proj_helper.py
stardust/geometry/ops3d/bbox/reflector.py
stardust/geometry/ops3d/bbox/structure/__init__.py
stardust/geometry/ops3d/bbox/structure/bbox_np_ops.py
stardust/geometry/ops3d/projection/__init__.py
stardust/geometry/ops3d/projection/helper.py
stardust_sdk-0.1.1.dist-info/licenses/LICENSE.txt
stardust_sdk-0.1.1.dist-info/METADATA
stardust_sdk-0.1.1.dist-info/WHEEL
stardust_sdk-0.1.1.dist-info/entry_points.txt
stardust_sdk-0.1.1.dist-info/top_level.txt
stardust_sdk-0.1.1.dist-info/RECORD
