Metadata-Version: 2.4
Name: stardust-sdk
Version: 0.1.1
Summary: Stardust SDK for AI/ML data processing and annotation workflows
Home-page: https://github.com/stardustai/Stardust-SDK
Author: stardust.ai
Author-email: support@stardust.ai
Project-URL: Bug Reports, https://github.com/stardustai/Stardust-SDK/issues
Project-URL: Source, https://github.com/stardustai/Stardust-SDK
Project-URL: Documentation, https://sdk-docs.stardust.ai/
Keywords: ai ml computer-vision annotation data-processing stardust
Classifier: Development Status :: 4 - Beta
Classifier: Intended Audience :: Developers
Classifier: Intended Audience :: Science/Research
Classifier: License :: OSI Approved :: MIT License
Classifier: Operating System :: OS Independent
Classifier: Programming Language :: Python :: 3
Classifier: Programming Language :: Python :: 3.9
Classifier: Programming Language :: Python :: 3.10
Classifier: Programming Language :: Python :: 3.11
Classifier: Programming Language :: Python :: 3.12
Classifier: Topic :: Scientific/Engineering :: Artificial Intelligence
Classifier: Topic :: Software Development :: Libraries :: Python Modules
Requires-Python: >=3.9
License-File: LICENSE.txt
Requires-Dist: numpy>=1.24.0
Requires-Dist: opencv-python>=4.8.0
Requires-Dist: open3d>=0.17.0
Requires-Dist: requests>=2.31.0
Requires-Dist: matplotlib>=3.7.0
Requires-Dist: pillow>=10.0.0
Requires-Dist: aiohttp>=3.9.0
Requires-Dist: httpx>=0.27.0
Requires-Dist: jsonlines>=4.0.0
Requires-Dist: numba>=0.58.0
Requires-Dist: pandas>=2.1.0
Requires-Dist: retry>=0.9.0
Requires-Dist: scipy>=1.11.0
Requires-Dist: shapely>=2.0.0
Requires-Dist: tqdm>=4.66.0
Requires-Dist: uvloop>=0.19.0
Provides-Extra: dev
Requires-Dist: pytest>=7.0; extra == "dev"
Requires-Dist: pytest-cov>=4.0; extra == "dev"
Requires-Dist: black>=23.0; extra == "dev"
Requires-Dist: flake8>=6.0; extra == "dev"
Dynamic: author
Dynamic: author-email
Dynamic: classifier
Dynamic: description
Dynamic: description-content-type
Dynamic: home-page
Dynamic: keywords
Dynamic: license-file
Dynamic: project-url
Dynamic: provides-extra
Dynamic: requires-dist
Dynamic: requires-python
Dynamic: summary
